forestadmin/datasource_django/__init__.py
forestadmin/datasource_django/collection.py
forestadmin/datasource_django/datasource.py
forestadmin/datasource_django/exception.py
forestadmin/datasource_django/interface.py
forestadmin/datasource_django/utils/__init__.py
forestadmin/datasource_django/utils/model_introspection.py
forestadmin/datasource_django/utils/native_driver_wrapper.py
forestadmin/datasource_django/utils/polymorphic_util.py
forestadmin/datasource_django/utils/query_factory.py
forestadmin/datasource_django/utils/record_serializer.py
forestadmin/datasource_django/utils/type_converter.py
forestadmin_datasource_django-1.23.9.dist-info/METADATA
forestadmin_datasource_django-1.23.9.dist-info/WHEEL
forestadmin_datasource_django-1.23.9.dist-info/RECORD
